bratuha_42.py
minecraft_parser_table_venom52_42_bratuha-0.0.1.dist-info/licenses/LICENSE.txt
minecraft_parser_table_venom52_42_bratuha-0.0.1.dist-info/METADATA
minecraft_parser_table_venom52_42_bratuha-0.0.1.dist-info/WHEEL
minecraft_parser_table_venom52_42_bratuha-0.0.1.dist-info/top_level.txt
minecraft_parser_table_venom52_42_bratuha-0.0.1.dist-info/RECORD
