Metadata-Version: 2.4
Name: minecraft_parser_table_venom52_42_bratuha
Version: 0.0.1
Summary: parser recipe from minecraft bratuha
Author-email: Venom52litvin <neformal.maximum@gmail.com>
License: MIT License
Classifier: Programming Language :: Python :: 3
Classifier: Operating System :: OS Independent
Requires-Python: >=3.10
License-File: LICENSE.txt
Requires-Dist: requests>=2.32.3
Requires-Dist: beautifulsoup4>=4.12.3
Requires-Dist: pandas>=2.2.3
Dynamic: license-file
